MANIFEST.in
setup.cfg
setup.py
src/pyroxy/__init__.py
src/pyroxy/config.py
src/pyroxy/exceptions.py
src/pyroxy/repositories.py
src/pyroxy.egg-info/PKG-INFO
src/pyroxy.egg-info/SOURCES.txt
src/pyroxy.egg-info/dependency_links.txt
src/pyroxy.egg-info/not-zip-safe
src/pyroxy.egg-info/requires.txt
src/pyroxy.egg-info/top_level.txt
src/pyroxy/controllers/__init__.py
src/pyroxy/controllers/simple.py
src/pyroxy/controllers/static.py
src/pyroxy/views/directory.tpl