Metadata-Version: 1.0
Name: pyroxy
Version: 0.1
Summary: A proxy for accessing PyPI
Home-page: https://github.com/amcfague/pyroxy
Author: Andrew McFague
Author-email: amcfague@gmail.com
License: UNKNOWN
Platform: UNKNOWN
